[
	{
		"__TYPE__": "SharedSliceContent",
		"variation": "default",
		"primary": {
			"heading": {
				"__TYPE__": "StructuredTextContent",
				"value": [
					{
						"type": "heading1",
						"content": {
							"text": "Require"
						}
					}
				]
			},
			"body": {
				"__TYPE__": "StructuredTextContent",
				"value": [
					{
						"type": "paragraph",
						"content": {
							"text": "Officia culpa cupidatat pariatur tempor dolor. Lorem consectetur aute dolor aliquip in ipsum ea fugiat nisi aliqua cupidatat non eiusmod. Ut aliquip excepteur occaecat Lorem proident exercitation adipisicing."
						}
					}
				]
			},
			"button": {
				"key": "9ade45c2-a300-4a85-b33a-02235ee99cfa",
				"__TYPE__": "LinkContent",
				"value": {
					"__TYPE__": "ExternalLink",
					"url": "http://twitter.com",
					"text": "bring"
				}
			},
			"skateboard_deck_texture": {
				"origin": {
					"id": "main",
					"url": "https://images.unsplash.com/photo-1579931794097-0ad001e51edb",
					"width": 3958,
					"height": 3958
				},
				"url": "https://images.unsplash.com/photo-1579931794097-0ad001e51edb",
				"width": 3958,
				"height": 3958,
				"edit": {
					"zoom": 1,
					"crop": {
						"x": 0,
						"y": 0
					},
					"background": "transparent"
				},
				"alt": "particularly",
				"credits": null,
				"__TYPE__": "ImageContent",
				"thumbnails": {}
			},
			"skateboard_wheel_texture": {
				"origin": {
					"id": "main",
					"url": "https://images.unsplash.com/photo-1531771686035-25f47595c87a",
					"width": 3024,
					"height": 3778
				},
				"url": "https://images.unsplash.com/photo-1531771686035-25f47595c87a",
				"width": 3024,
				"height": 3778,
				"edit": {
					"zoom": 1,
					"crop": {
						"x": 0,
						"y": 0
					},
					"background": "transparent"
				},
				"alt": "war",
				"credits": null,
				"__TYPE__": "ImageContent",
				"thumbnails": {}
			},
			"skateboard_truck_color": {
				"__TYPE__": "FieldContent",
				"value": "#9dbdf4",
				"type": "Color"
			},
			"skateboard_bolt_color": {
				"__TYPE__": "FieldContent",
				"value": "#011d4b",
				"type": "Color"
			}
		},
		"items": []
	}
]